artmetyka/__init__.py
artmetyka/arth_operations.py
test/__init__.py
test/add.py
test/sub.py
test_technologii-0.0.1.dist-info/METADATA
test_technologii-0.0.1.dist-info/WHEEL
test_technologii-0.0.1.dist-info/top_level.txt
test_technologii-0.0.1.dist-info/RECORD
