Metadata-Version: 2.1
Name: test-technologii
Version: 0.0.1
Summary: super opis
Home-page: UNKNOWN
License: UNKNOWN
Platform: UNKNOWN
